lab7/t_ff.vhd
library IEEE;
use IEEE.STD_LOGIC_1164.ALL;

entity T_FF is
    port(
        CLK : in std_logic;
        T   : in std_logic;
        Q   : out std_logic;
        QB  : out std_logic
    );
end entity T_FF;

architecture Behavioral of T_FF is
    signal Q_int : std_logic := '0';
begin
    process(CLK)
    begin
        if rising_edge(CLK) then
            if T='1' then
                Q_int <= not Q_int;
            end if;
        end if;
    end process;

    Q <= Q_int;
    QB <= not Q_int;
end architecture Behavioral;

lab7/jk_ff.vhd
library IEEE;
use IEEE.STD_LOGIC_1164.ALL;

entity JK_FF is
    port(
        CLK : in std_logic;
        J   : in std_logic;
        K   : in std_logic;
        Q   : out std_logic;
        QB  : out std_logic
    );
end entity JK_FF;

architecture Behavioral of JK_FF is
    signal Q_int : std_logic := '0';
begin
    process(CLK)
    begin
        if rising_edge(CLK) then
            if J='0' and K='0' then
                null;
            elsif J='0' and K='1' then
                Q_int <= '0';
            elsif J='1' and K='0' then
                Q_int <= '1';
            else
                Q_int <= not Q_int;
            end if;
        end if;
    end process;

    Q <= Q_int;
    QB <= not Q_int;
end architecture Behavioral;

lab7/d_ff.vhd
library IEEE;
use IEEE.STD_LOGIC_1164.ALL;

entity D_FF is
    port(
        CLK : in std_logic;
        D   : in std_logic;
        Q   : out std_logic;
        QB  : out std_logic
    );
end entity D_FF;

architecture Behavioral of D_FF is
    signal Q_int : std_logic := '0';
begin
    process(CLK)
    begin
        if rising_edge(CLK) then
            Q_int <= D;
        end if;
    end process;

    Q <= Q_int;
    QB <= not Q_int;
end architecture Behavioral;

lab7/sr_ff.vhd
library IEEE;
use IEEE.STD_LOGIC_1164.ALL;

entity SR_FF is
    port(
        CLK : in std_logic;
        S   : in std_logic;
        R   : in std_logic;
        Q   : out std_logic;
        QB  : out std_logic
    );
end entity SR_FF;

architecture Behavioral of SR_FF is
    signal Q_int : std_logic := '0';
begin
    process(CLK)
    begin
        if rising_edge(CLK) then
            if S='0' and R='0' then
                null;
            elsif S='0' and R='1' then
                Q_int <= '0';
            elsif S='1' and R='0' then
                Q_int <= '1';
            end if;
        end if;
    end process;

    Q <= Q_int;
    QB <= not Q_int;
end architecture Behavioral;

lab7/ff_tb.vhd
library IEEE;
use IEEE.STD_LOGIC_1164.ALL;

entity FF_TB is
end entity FF_TB;

architecture Simulation of FF_TB is

    signal CLK : std_logic := '0';
    signal S, R : std_logic := '0';
    signal D : std_logic := '0';
    signal J, K : std_logic := '0';
    signal T : std_logic := '0';

    signal Q_SR, Q_D, Q_JK, Q_T : std_logic;
    signal QB_SR, QB_D, QB_JK, QB_T : std_logic;

    constant CLK_PERIOD : time := 20 ns;
    signal sim_running : boolean := true;

begin

    -- Clock generation
    CLK <= not CLK after CLK_PERIOD/2 when sim_running else CLK;

    -- Instantiate Flip-Flops
    U1 : entity work.SR_FF
        port map (
            CLK => CLK,
            S   => S,
            R   => R,
            Q   => Q_SR,
            QB  => QB_SR
        );

    U2 : entity work.D_FF
        port map (
            CLK => CLK,
            D   => D,
            Q   => Q_D,
            QB  => QB_D
        );

    U3 : entity work.JK_FF
        port map (
            CLK => CLK,
            J   => J,
            K   => K,
            Q   => Q_JK,
            QB  => QB_JK
        );

    U4 : entity work.T_FF
        port map (
            CLK => CLK,
            T   => T,
            Q   => Q_T,
            QB  => QB_T
        );

    -- Test Stimulus
    STIMULUS : process
    begin

        -- SR Flip-Flop Test
        S <= '1'; R <= '0';
        wait for 40 ns;

        S <= '0'; R <= '1';
        wait for 40 ns;

        S <= '0'; R <= '0';
        wait for 40 ns;

        -- D Flip-Flop Test
        D <= '1';
        wait for 40 ns;

        D <= '0';
        wait for 40 ns;

        -- JK Flip-Flop Test
        J <= '1'; K <= '0';
        wait for 40 ns;

        J <= '1'; K <= '1';
        wait for 40 ns;

        J <= '0'; K <= '1';
        wait for 40 ns;

        -- T Flip-Flop Test
        T <= '1';
        wait for 80 ns;

        T <= '0';
        wait for 40 ns;

        sim_running <= false;
        wait;

    end process;

end architecture Simulation;

lab7/flipflops.vcd
$date
  Sun Jul 12 14:26:11 2026
$end
$version
  GHDL v0
$end
$timescale
  1 fs
$end
$scope module standard $end
$upscope $end
$scope module std_logic_1164 $end
$upscope $end
$scope module ff_tb $end
$var reg 1 ! clk $end
$var reg 1 " s $end
$var reg 1 # r $end
$var reg 1 $ d $end
$var reg 1 % j $end
$var reg 1 & k $end
$var reg 1 ' t $end
$var reg 1 ( q_sr $end
$var reg 1 ) q_d $end
$var reg 1 * q_jk $end
$var reg 1 + q_t $end
$var reg 1 , qb_sr $end
$var reg 1 - qb_d $end
$var reg 1 . qb_jk $end
$var reg 1 / qb_t $end
$var reg 1 0 sim_running $end
$scope module u1 $end
$var reg 1 1 clk $end
$var reg 1 2 s $end
$var reg 1 3 r $end
$var reg 1 4 q $end
$var reg 1 5 qb $end
$var reg 1 6 q_int $end
$upscope $end
$scope module u2 $end
$var reg 1 7 clk $end
$var reg 1 8 d $end
$var reg 1 9 q $end
$var reg 1 : qb $end
$var reg 1 ; q_int $end
$upscope $end
$scope module u3 $end
$var reg 1 < clk $end
$var reg 1 = j $end
$var reg 1 > k $end
$var reg 1 ? q $end
$var reg 1 @ qb $end
$var reg 1 A q_int $end
$upscope $end
$scope module u4 $end
$var reg 1 B clk $end
$var reg 1 C t $end
$var reg 1 D q $end
$var reg 1 E qb $end
$var reg 1 F q_int $end
$upscope $end
$upscope $end
$enddefinitions $end
#0
0!
1"
0#
0$
0%
0&
0'
0(
0)
0*
0+
1,
1-
1.
1/
10
01
12
03
04
15
06
07
08
09
1:
0;
0<
0=
0>
0?
1@
0A
0B
0C
0D
1E
0F
#10000000
1!
1(
0,
11
14
05
16
17
1<
1B
#20000000
0!
01
07
0<
0B
#30000000
1!
11
17
1<
1B
#40000000
0!
0"
1#
01
02
13
07
0<
0B
#50000000
1!
0(
1,
11
04
15
06
17
1<
1B
#60000000
0!
01
07
0<
0B
#70000000
1!
11
17
1<
1B
#80000000
0!
0#
01
03
07
0<
0B
#90000000
1!
11
17
1<
1B
#100000000
0!
01
07
0<
0B
#110000000
1!
11
17
1<
1B
#120000000
0!
1$
01
07
18
0<
0B
#130000000
1!
1)
0-
11
17
19
0:
1;
1<
1B
#140000000
0!
01
07
0<
0B
#150000000
1!
11
17
1<
1B
#160000000
0!
0$
01
07
08
0<
0B
#170000000
1!
0)
1-
11
17
09
1:
0;
1<
1B
#180000000
0!
01
07
0<
0B
#190000000
1!
11
17
1<
1B
#200000000
0!
1%
01
07
0<
1=
0B
#210000000
1!
1*
0.
11
17
1<
1?
0@
1A
1B
#220000000
0!
01
07
0<
0B
#230000000
1!
11
17
1<
1B
#240000000
0!
1&
01
07
0<
1>
0B
#250000000
1!
0*
1.
11
17
1<
0?
1@
0A
1B
#260000000
0!
01
07
0<
0B
#270000000
1!
1*
0.
11
17
1<
1?
0@
1A
1B
#280000000
0!
0%
01
07
0<
0=
0B
#290000000
1!
0*
1.
11
17
1<
0?
1@
0A
1B
#300000000
0!
01
07
0<
0B
#310000000
1!
11
17
1<
1B
#320000000
0!
1'
01
07
0<
0B
1C
#330000000
1!
1+
0/
11
17
1<
1B
1D
0E
1F
#340000000
0!
01
07
0<
0B
#350000000
1!
0+
1/
11
17
1<
1B
0D
1E
0F
#360000000
0!
01
07
0<
0B
#370000000
1!
1+
0/
11
17
1<
1B
1D
0E
1F
#380000000
0!
01
07
0<
0B
#390000000
1!
0+
1/
11
17
1<
1B
0D
1E
0F
#400000000
0!
0'
01
07
0<
0B
0C
#410000000
1!
11
17
1<
1B
#420000000
0!
01
07
0<
0B
#430000000
1!
11
17
1<
1B
#440000000
0!
00
01
07
0<
0B
